swiftdeploy/__init__.py
swiftdeploy/app.py
swiftdeploy/model.py
swiftdeploy/settings.py
swiftdeploy/html/__init__.py
swiftdeploy/html/config.py
swiftdeploy/html/htmlcontent.py
swiftdeploy/html/tags.py
swiftdeploy/html/utils.py
swiftdeply-0.5.dist-info/LICENSE
swiftdeply-0.5.dist-info/METADATA
swiftdeply-0.5.dist-info/WHEEL
swiftdeply-0.5.dist-info/top_level.txt
swiftdeply-0.5.dist-info/RECORD
