Metadata-Version: 2.1
Name: swiftdeply
Version: 0.5
Summary: This package provides a web application wrapper for your machine learning models.
Home-page: https://github.com/firebreather-heart/swiftdeploy
Author: Akinrotimi Daniel F
Author-email: dtenny95@gmail.com
Classifier: Programming Language :: Python :: 3
Classifier: License :: OSI Approved :: Apache Software License
Classifier: Operating System :: OS Independent
Requires-Python: >=3.6
License-File: LICENSE
Requires-Dist: Flask
